Metadata-Version: 1.1
Name: pprofile
Version: 2.0.4
Summary: Line-granularity, thread-aware deterministic and statistic pure-python profiler
Home-page: http://github.com/vpelletier/pprofile
Author: Vincent Pelletier
Author-email: plr.vincent@gmail.com
License: GPL 2+
Platform: any
Classifier: Intended Audience :: Developers
Classifier: License :: OSI Approved :: GNU General Public License v2 or later (GPLv2+)
Classifier: Operating System :: OS Independent
Classifier: Programming Language :: Python :: 2.7
Classifier: Programming Language :: Python :: 3
Classifier: Programming Language :: Python :: Implementation :: PyPy
Classifier: Programming Language :: Python :: Implementation :: CPython
Classifier: Programming Language :: Python :: Implementation :: IronPython
Classifier: Topic :: Software Development
